unithash/__init__.py
unithash/find.py
unithash-0.1.0.dist-info/LICENSE
unithash-0.1.0.dist-info/METADATA
unithash-0.1.0.dist-info/WHEEL
unithash-0.1.0.dist-info/top_level.txt
unithash-0.1.0.dist-info/RECORD
