Metadata-Version: 2.1
Name: unithash
Version: 0.1.0
Summary: Find the unit digit hash of a number by recursively calling the sum of all digits in a number till reaching units place
Home-page: UNKNOWN
Author: Aditya Chellam
Author-email: UNKNOWN
License: MIT
Platform: UNKNOWN
Requires-Dist: regex
